ullyses/__init__.py
ullyses/_release.py
ullyses/analyze_variability.py
ullyses/apply_cos_shifts.py
ullyses/calibrate_stis_data.py
ullyses/coadd.py
ullyses/combine_header_keys.py
ullyses/create_ullyses_hlsp.py
ullyses/flag_vignetting.py
ullyses/fuse_add_dq.py
ullyses/generic_coadd_wrapper.py
ullyses/imaging_hlsps_wrapper.py
ullyses/lcogt_hlsps_wrapper.py
ullyses/make_flagged_fuse.py
ullyses/make_preview_plots.py
ullyses/make_stis_x1ds.py
ullyses/plot_stis_data.py
ullyses/splittag_wrapper.py
ullyses/stis_coadd_x1d.py
ullyses/stisblazefix_wrapper.py
ullyses/timeseries.py
ullyses/timeseries_wrapper.py
ullyses/ullyses_coadd_abut_wrapper.py
ullyses/ullyses_hlsp.py
ullyses/unflag_echelle_orders.py
ullyses/tests/__init__.py
ullyses/tests/test_wrapper.py
ullyses-4.1.0.dist-info/LICENSE
ullyses-4.1.0.dist-info/METADATA
ullyses-4.1.0.dist-info/WHEEL
ullyses-4.1.0.dist-info/entry_points.txt
ullyses-4.1.0.dist-info/top_level.txt
ullyses-4.1.0.dist-info/RECORD
