Metadata-Version: 2.1
Name: ullyses
Version: 4.1.0
Summary: Create ULLYSES data products
Author-email: ULLYSES STScI Team <ullyses_dp@stsci.edu>
License: BSD 3-Clause License
Keywords: astronomy
Classifier: Programming Language :: Python
Classifier: Programming Language :: Python :: 3
Classifier: Development Status :: 1 - Planning
Classifier: Intended Audience :: Science/Research
Classifier: Topic :: Scientific/Engineering :: Astronomy
Classifier: Topic :: Scientific/Engineering :: Physics
Classifier: Topic :: Software Development :: Libraries :: Python Modules
Requires-Python: >=3.9
License-File: LICENSE
Requires-Dist: datetime
Requires-Dist: numpy >=1.22.4
Requires-Dist: cython
Requires-Dist: astropy >=6.0.0
Requires-Dist: ullyses-utils >=3.1.0
Requires-Dist: pandas >2.0
Requires-Dist: calcos >=3.4.0
Requires-Dist: costools
Requires-Dist: stistools >=1.4.2
Requires-Dist: matplotlib
Requires-Dist: pyyaml
Requires-Dist: plotly
Requires-Dist: scipy >=1.11.4
Requires-Dist: hasp >=0.9.6
